{
    "type": "Feature",
    "stac_version": "0.8.1",
    "id": "982a1f-labels",
    "properties": {
        "datetime": "2017-11-15 00:00:00Z",
        "license": "ODbL-1.0",
        "label:overviews": [
            {
                "property_key": [
                    "building"
                ],
                "counts": [
                    {
                        "name": "yes",
                        "count": 3597
                    }
                ]
            }
        ],
        "label:description": "Geojson building labels for scene 982a1f",
        "area": "nia",
        "label:properties": [
            "building"
        ],
        "label:type": "vector",
        "label:classes": [
            {
                "name": "building",
                "classes": [
                    "yes"
                ]
            }
        ]
    },
    "geometry": {
        "coordinates": [
            [
                [
                    2.141596223576107,
                    13.463825295414388
                ],
                [
                    2.1415773267146294,
                    13.463864076580137
                ],
                [
                    2.141576973317662,
                    13.463975711770223
                ],
                [
                    2.141595271993293,
                    13.464063540328901
                ],
                [
                    2.141641273498445,
                    13.464118342004484
                ],
                [
                    2.141669738309242,
                    13.464120450596866
                ],
                [
                    2.1417035851928965,
                    13.464157349681791
                ],
                [
                    2.1418454241870832,
                    13.464347926152222
                ],
                [
                    2.1418298089530645,
                    13.464460256143404
                ],
                [
                    2.1416296633042076,
                    13.464646261206202
                ],
                [
                    2.141681544570977,
                    13.465304060342115
                ],
                [
                    2.141621928937875,
                    13.465393429369467
                ],
                [
                    2.1415467867650193,
                    13.465563595865522
                ],
                [
                    2.1415173494598188,
                    13.46558102783418
                ],
                [
                    2.1413944987637463,
                    13.465856989389586
                ],
                [
                    2.1413387790161496,
                    13.465921719868762
                ],
                [
                    2.1413249744198213,
                    13.465985071680874
                ],
                [
                    2.141281897775868,
                    13.46605011619103
                ],
                [
                    2.141202738503752,
                    13.466237852381868
                ],
                [
                    2.141151895703656,
                    13.466304979408399
                ],
                [
                    2.141149713872772,
                    13.466344822386104
                ],
                [
                    2.141126038288899,
                    13.466363764719846
                ],
                [
                    2.1410735219022805,
                    13.466466577086042
                ],
                [
                    2.140967721504878,
                    13.466709048908871
                ],
                [
                    2.1409334290285322,
                    13.466740048440954
                ],
                [
                    2.1409330678847693,
                    13.466786183908653
                ],
                [
                    2.14089927005265,
                    13.466816335141653
                ],
                [
                    2.1408372719181954,
                    13.466961809534896
                ],
                [
                    2.140785895521908,
                    13.46702892841835
                ],
                [
                    2.140767693397876,
                    13.467097879522155
                ],
                [
                    2.1407426110374237,
                    13.467114505205124
                ],
                [
                    2.140654285011932,
                    13.467319884869022
                ],
                [
                    2.1406122495597906,
                    13.467361117355402
                ],
                [
                    2.1404638126387563,
                    13.467685675181157
                ],
                [
                    2.140469182736032,
                    13.467714711244897
                ],
                [
                    2.140425207596534,
                    13.467826066893448
                ],
                [
                    2.1403941709987517,
                    13.467839315650217
                ],
                [
                    2.140393326290883,
                    13.467881959879097
                ],
                [
                    2.1403339849133602,
                    13.468001810655261
                ],
                [
                    2.1403323365506104,
                    13.468047313291631
                ],
                [
                    2.1403060370459825,
                    13.468099268596452
                ],
                [
                    2.140280580641346,
                    13.468112075002997
                ],
                [
                    2.1402671240813915,
                    13.4681793832346
                ],
                [
                    2.1402811488729996,
                    13.468213508162679
                ],
                [
                    2.140245496031578,
                    13.46829431886749
                ],
                [
                    2.1402460043400917,
                    13.468348896017744
                ],
                [
                    2.1402762977613703,
                    13.468363100359843
                ],
                [
                    2.140237075349301,
                    13.46853194226524
                ],
                [
                    2.140253758911136,
                    13.468570365288649
                ],
                [
                    2.140254038219845,
                    13.468644493495667
                ],
                [
                    2.140215036425084,
                    13.468761886176381
                ],
                [
                    2.1402365085871318,
                    13.468830503114953
                ],
                [
                    2.140140956527007,
                    13.469383926208952
                ],
                [
                    2.1401061613883448,
                    13.469452467817487
                ],
                [
                    2.140075674819855,
                    13.46943110895205
                ],
                [
                    2.1400383412345803,
                    13.469455541367521
                ],
                [
                    2.1400279432158724,
                    13.469494822037104
                ],
                [
                    2.1399853419731905,
                    13.469542025986376
                ],
                [
                    2.139966653033485,
                    13.469594829883647
                ],
                [
                    2.1399420727662584,
                    13.469601283992926
                ],
                [
                    2.1399234824009943,
                    13.469648317392412
                ],
                [
                    2.1398700158820834,
                    13.469639788949515
                ],
                [
                    2.1398384606876015,
                    13.469668370529464
                ],
                [
                    2.1397663028053744,
                    13.469793204000132
                ],
                [
                    2.139690084703863,
                    13.469779145150115
                ],
                [
                    2.1396059480704515,
                    13.469941903236325
                ],
                [
                    2.139576360027055,
                    13.46995966567784
                ],
                [
                    2.1395502485121387,
                    13.470048505504487
                ],
                [
                    2.139526124352389,
                    13.470041959022582
                ],
                [
                    2.13950594844186,
                    13.470084166260538
                ],
                [
                    2.139463783185903,
                    13.470077608186187
                ],
                [
                    2.1394624493353107,
                    13.470099866974953
                ],
                [
                    2.1394287986020926,
                    13.470125056823663
                ],
                [
                    2.139332557640294,
                    13.470283626444697
                ],
                [
                    2.1393050957378574,
                    13.470355451763139
                ],
                [
                    2.1391996734647276,
                    13.470352857740439
                ],
                [
                    2.1391922687080585,
                    13.470407508073567
                ],
                [
                    2.1391484934199765,
                    13.470491729774013
                ],
                [
                    2.1390102954078425,
                    13.470488048941975
                ],
                [
                    2.1390093785695385,
                    13.47059149648219
                ],
                [
                    2.138974559636955,
                    13.47064110851391
                ],
                [
                    2.1389746056212484,
                    13.470730730362222
                ],
                [
                    2.138939803207411,
                    13.470775699790542
                ],
                [
                    2.138931012560832,
                    13.470902179805726
                ],
                [
                    2.138905157760787,
                    13.470940845270425
                ],
                [
                    2.1389050007199555,
                    13.4710256194524
                ],
                [
                    2.1388700026437197,
                    13.471125281315583
                ],
                [
                    2.1388784184021374,
                    13.471156437682785
                ],
                [
                    2.1388531321061928,
                    13.471188257085975
                ],
                [
                    2.1388524523726242,
                    13.471267055757203
                ],
                [
                    2.13881833937238,
                    13.471332964622468
                ],
                [
                    2.1387913413770456,
                    13.47146876219428
                ],
                [
                    2.1387488991058095,
                    13.471515054586616
                ],
                [
                    2.1387304967261755,
                    13.471595981468694
                ],
                [
                    2.138688004433465,
                    13.471612547313171
                ],
                [
                    2.13864353013205,
                    13.471743945640686
                ],
                [
                    2.1385834379297433,
                    13.471838750485379
                ],
                [
                    2.1385650323940637,
                    13.471920982019821
                ],
                [
                    2.138514321523039,
                    13.471953253354622
                ],
                [
                    2.138504294193586,
                    13.47201797258616
                ],
                [
                    2.1384614048354877,
                    13.472103795964784
                ],
                [
                    2.138465275712701,
                    13.472127182748752
                ],
                [
                    2.1384195116444387,
                    13.472122904043452
                ],
                [
                    2.1383827224358676,
                    13.472246728160282
                ],
                [
                    2.138353577938926,
                    13.472247316464369
                ],
                [
                    2.1383398102410953,
                    13.472264941295446
                ],
                [
                    2.138321401934762,
                    13.472347465412662
                ],
                [
                    2.1382701523736833,
                    13.472422308117002
                ],
                [
                    2.1382605440610174,
                    13.472478239830979
                ],
                [
                    2.138200568860539,
                    13.472558909508356
                ],
                [
                    2.1381909014176332,
                    13.47263134700061
                ],
                [
                    2.1381309108064515,
                    13.472716276241142
                ],
                [
                    2.138112431180644,
                    13.472825665365454
                ],
                [
                    2.138079158619463,
                    13.472821558268846
                ],
                [
                    2.138034297556054,
                    13.47298506076572
                ],
                [
                    2.1380004041221343,
                    13.473001755000292
                ],
                [
                    2.1379907963315157,
                    13.47305751480737
                ],
                [
                    2.13795592153003,
                    13.473122567592524
                ],
                [
                    2.1379605090201514,
                    13.473159281029403
                ],
                [
                    2.1379473633716852,
                    13.473183946858374
                ],
                [
                    2.137905172663631,
                    13.473188749948841
                ],
                [
                    2.1378914029271328,
                    13.473206907237376
                ],
                [
                    2.1378949469583883,
                    13.473236261501926
                ],
                [
                    2.1378561097953304,
                    13.473344257341669
                ],
                [
                    2.1378601580746976,
                    13.47337961549211
                ],
                [
                    2.137847064943583,
                    13.473396607817403
                ],
                [
                    2.1378155914275494,
                    13.473398527660885
                ],
                [
                    2.1377765834976885,
                    13.473452007597379
                ],
                [
                    2.137748468863378,
                    13.473575681150976
                ],
                [
                    2.137701030524914,
                    13.473583083606682
                ],
                [
                    2.1376774319222003,
                    13.473669173250133
                ],
                [
                    2.137608719688822,
                    13.473751699814581
                ],
                [
                    2.1376077828108735,
                    13.473819901353666
                ],
                [
                    2.1375692649181635,
                    13.473897226589429
                ],
                [
                    2.1375443207544595,
                    13.474044687559218
                ],
                [
                    2.13752252046971,
                    13.474056532758217
                ],
                [
                    2.137504098950281,
                    13.474100628834172
                ],
                [
                    2.1374943767888936,
                    13.47418875098744
                ],
                [
                    2.1374518933803124,
                    13.474245808833647
                ],
                [
                    2.1374510175227335,
                    13.474296972090725
                ],
                [
                    2.1374165827033442,
                    13.47438795083686
                ],
                [
                    2.137424998513468,
                    13.474419064381104
                ],
                [
                    2.1373988218853346,
                    13.474485860887267
                ],
                [
                    2.137398887654023,
                    13.474569775123022
                ],
                [
                    2.137381559449591,
                    13.474596551513056
                ],
                [
                    2.1373899599690276,
                    13.47463192457619
                ],
                [
                    2.1373467246315765,
                    13.474861793944687
                ],
                [
                    2.1372073194786707,
                    13.475049246007362
                ],
                [
                    2.137182721385278,
                    13.475053179806602
                ],
                [
                    2.137198404909862,
                    13.475100399282264
                ],
                [
                    2.1371115629791246,
                    13.475194347890229
                ],
                [
                    2.1370875245435026,
                    13.475200161648687
                ],
                [
                    2.137085495981523,
                    13.4752305498112
                ],
                [
                    2.137175965821527,
                    13.475320745549238
                ],
                [
                    2.137207395763952,
                    13.475331425005285
                ],
                [
                    2.137259374132402,
                    13.475394118561232
                ],
                [
                    2.1372163108508273,
                    13.475581364131493
                ],
                [
                    2.137228122000972,
                    13.475644655048514
                ],
                [
                    2.1372604083909086,
                    13.475639896382537
                ],
                [
                    2.1373269563701807,
                    13.475672215145094
                ],
                [
                    2.1374422316050175,
                    13.475689481830928
                ],
                [
                    2.137509578115563,
                    13.475722892668868
                ],
                [
                    2.1376960640471943,
                    13.475757464800418
                ],
                [
                    2.1378897458051647,
                    13.475934450227285
                ],
                [
                    2.1379654525616347,
                    13.47598219394181
                ],
                [
                    2.1380378160171376,
                    13.476062214211098
                ],
                [
                    2.1380692198239215,
                    13.47607289351465
                ],
                [
                    2.1381072429029464,
                    13.476121554567744
                ],
                [
                    2.138223051804238,
                    13.476200677168002
                ],
                [
                    2.138342117710501,
                    13.476317769934443
                ],
                [
                    2.138387929663568,
                    13.476337017850447
                ],
                [
                    2.138404945310345,
                    13.476361566281001
                ],
                [
                    2.1384305269321926,
                    13.476362189187165
                ],
                [
                    2.1384404933691346,
                    13.47638709281763
                ],
                [
                    2.138459884390911,
                    13.476384541911127
                ],
                [
                    2.1386013773988046,
                    13.476199978259789
                ],
                [
                    2.138625435796561,
                    13.47618863503959
                ],
                [
                    2.1386445696263094,
                    13.47614089101841
                ],
                [
                    2.1386860391267706,
                    13.47612920833297
                ],
                [
                    2.1386995563903453,
                    13.476089964186734
                ],
                [
                    2.13878292989051,
                    13.47610675604109
                ],
                [
                    2.139058543950549,
                    13.476235333360526
                ],
                [
                    2.13918336483366,
                    13.476268928926944
                ],
                [
                    2.139620591651532,
                    13.476464382274635
                ],
                [
                    2.139660284886538,
                    13.47646119449248
                ],
                [
                    2.1397242525594207,
                    13.476362363503188
                ],
                [
                    2.1397841413142142,
                    13.476371087826545
                ],
                [
                    2.1399636206630026,
                    13.476454076554079
                ],
                [
                    2.1400101665852636,
                    13.476455989051644
                ],
                [
                    2.140242322253792,
                    13.476566313064133
                ],
                [
                    2.140349716615262,
                    13.476592394005042
                ],
                [
                    2.140547113989172,
                    13.476685560332335
                ],
                [
                    2.1406106707669212,
                    13.476694452799117
                ],
                [
                    2.1407392318858727,
                    13.476754137846303
                ],
                [
                    2.140764582312933,
                    13.476745562170171
                ],
                [
                    2.140869654630296,
                    13.476796647630907
                ],
                [
                    2.140964582847855,
                    13.476813824083058
                ],
                [
                    2.140994814820404,
                    13.476775608787104
                ],
                [
                    2.141033407332923,
                    13.476788545298149
                ],
                [
                    2.1410600952819707,
                    13.476770234189733
                ],
                [
                    2.141124606090947,
                    13.476771286215028
                ],
                [
                    2.1413574336242123,
                    13.476864871981384
                ],
                [
                    2.141385753450418,
                    13.476856304664548
                ],
                [
                    2.1414704771624056,
                    13.476898802796903
                ],
                [
                    2.141516218309046,
                    13.476899348422325
                ],
                [
                    2.1417689769154293,
                    13.477017728188114
                ],
                [
                    2.1418183608850447,
                    13.4770185779123
                ],
                [
                    2.1419950036841198,
                    13.477102627791778
                ],
                [
                    2.1420800670890436,
                    13.477120645044188
                ],
                [
                    2.142188748878513,
                    13.477172807118526
                ],
                [
                    2.142210119073336,
                    13.47716315283237
                ],
                [
                    2.142332204785573,
                    13.477222282589878
                ],
                [
                    2.1423775280110844,
                    13.477222826667644
                ],
                [
                    2.142497386924626,
                    13.477281948745548
                ],
                [
                    2.142543628426971,
                    13.477282495928849
                ],
                [
                    2.1426335854458136,
                    13.477324692945407
                ],
                [
                    2.1426569870470806,
                    13.477318333851809
                ],
                [
                    2.1427596545255296,
                    13.47736771940767
                ],
                [
                    2.142845896902025,
                    13.477384519743367
                ],
                [
                    2.1428737769038064,
                    13.477350694227534
                ],
                [
                    2.1430594451867724,
                    13.477422836856993
                ],
                [
                    2.143231629634463,
                    13.477453065559363
                ],
                [
                    2.1433333648883246,
                    13.477503638981874
                ],
                [
                    2.1434021791382434,
                    13.477512249779421
                ],
                [
                    2.143558540167959,
                    13.477588235326168
                ],
                [
                    2.1435977770027796,
                    13.47758478728057
                ],
                [
                    2.143785110261665,
                    13.47767366768543
                ],
                [
                    2.143814809778537,
                    13.477659892500123
                ],
                [
                    2.143967672631695,
                    13.47774191130287
                ],
                [
                    2.1440600291506424,
                    13.47775072738306
                ],
                [
                    2.1440968258285333,
                    13.477665834168171
                ],
                [
                    2.144172538121677,
                    13.477683087049256
                ],
                [
                    2.144197269374977,
                    13.477660864641605
                ],
                [
                    2.1442675881139643,
                    13.477511977398382
                ],
                [
                    2.1442767394076596,
                    13.477444199119201
                ],
                [
                    2.1444675189221143,
                    13.47704706580617
                ],
                [
                    2.144476613060087,
                    13.476982371578975
                ],
                [
                    2.144580904132612,
                    13.476764949348562
                ],
                [
                    2.1445771436026386,
                    13.47671033972101
                ],
                [
                    2.1446071221561693,
                    13.476644908703749
                ],
                [
                    2.144601219592811,
                    13.47661756698212
                ],
                [
                    2.144633346452987,
                    13.476552147111551
                ],
                [
                    2.1446685440149778,
                    13.476404779512599
                ],
                [
                    2.1447116451541226,
                    13.476321001210563
                ],
                [
                    2.1447033342529482,
                    13.476260073605625
                ],
                [
                    2.1447809954389716,
                    13.476101433340345
                ],
                [
                    2.1448165012216025,
                    13.47595323132358
                ],
                [
                    2.144859378823666,
                    13.475870312973397
                ],
                [
                    2.144859933786414,
                    13.475825590739507
                ],
                [
                    2.1449463618922198,
                    13.475649944308923
                ],
                [
                    2.1450076522995487,
                    13.475482659912574
                ],
                [
                    2.145007654650008,
                    13.475440841980456
                ],
                [
                    2.145068632239644,
                    13.475316742413286
                ],
                [
                    2.1450686237861385,
                    13.47527493067024
                ],
                [
                    2.145216345806816,
                    13.474933346890202
                ],
                [
                    2.145216902489525,
                    13.474888624658094
                ],
                [
                    2.1452813544094305,
                    13.474772538056376
                ],
                [
                    2.145347491456789,
                    13.4745758756721
                ],
                [
                    2.1454947785465506,
                    13.474269564112854
                ],
                [
                    2.1454951043133734,
                    13.47422265217966
                ],
                [
                    2.1456423735002206,
                    13.473919179900358
                ],
                [
                    2.145643234696004,
                    13.473874688167461
                ],
                [
                    2.145695021797173,
                    13.4738011545075
                ],
                [
                    2.1457040829845306,
                    13.473738588464288
                ],
                [
                    2.1458696822750314,
                    13.473380809744233
                ],
                [
                    2.145912159921232,
                    13.473324282959195
                ],
                [
                    2.1459217616253388,
                    13.473269729918597
                ],
                [
                    2.1459647832846906,
                    13.47321317920097
                ],
                [
                    2.145973812794835,
                    13.473159156755285
                ],
                [
                    2.145997821517255,
                    13.473145939789063
                ],
                [
                    2.146017665093734,
                    13.473074113356112
                ],
                [
                    2.1460335319068777,
                    13.473070148979172
                ],
                [
                    2.1460563192590794,
                    13.47302180750272
                ],
                [
                    2.146104885554131,
                    13.472872296131678
                ],
                [
                    2.1461385779458753,
                    13.472838390904576
                ],
                [
                    2.146156948173267,
                    13.47275881797483
                ],
                [
                    2.1461911841786736,
                    13.472732079190823
                ],
                [
                    2.146200274969454,
                    13.472668158483387
                ],
                [
                    2.146225776317139,
                    13.472642744744459
                ],
                [
                    2.146235364667101,
                    13.472591925821495
                ],
                [
                    2.1462913719954577,
                    13.47248825340692
                ],
                [
                    2.146290674538991,
                    13.47245132589901
                ],
                [
                    2.1463126162531174,
                    13.47243884769614
                ],
                [
                    2.146352274693368,
                    13.4723436332302
                ],
                [
                    2.1463484165702598,
                    13.472315934456162
                ],
                [
                    2.146382529492605,
                    13.472250024295535
                ],
                [
                    2.1464007086578536,
                    13.472145220407006
                ],
                [
                    2.146417440326313,
                    13.472138098399077
                ],
                [
                    2.146444141476845,
                    13.472017553659372
                ],
                [
                    2.146461205973212,
                    13.472002701137706
                ],
                [
                    2.146461762384368,
                    13.471957978787932
                ],
                [
                    2.1465178164901766,
                    13.471841027885816
                ],
                [
                    2.146515078802031,
                    13.471804691731128
                ],
                [
                    2.1465428991495465,
                    13.47178311591011
                ],
                [
                    2.146548482276966,
                    13.471736266330387
                ],
                [
                    2.1466601872496835,
                    13.471715588902802
                ],
                [
                    2.1467054060376873,
                    13.471523260031843
                ],
                [
                    2.1470614348478683,
                    13.470955578014685
                ],
                [
                    2.147058131577129,
                    13.470927550676947
                ],
                [
                    2.1470138334444577,
                    13.470925876516949
                ],
                [
                    2.1468140169733028,
                    13.470961166507704
                ],
                [
                    2.1468919997705456,
                    13.470801353590778
                ],
                [
                    2.1469046489831345,
                    13.470637417268257
                ],
                [
                    2.1469667812002524,
                    13.470641855552248
                ],
                [
                    2.146981763345016,
                    13.470630125065076
                ],
                [
                    2.1470258043758315,
                    13.470503101819938
                ],
                [
                    2.1470270318149556,
                    13.47046377986595
                ],
                [
                    2.146994015312409,
                    13.470379502559107
                ],
                [
                    2.1470101312933645,
                    13.470278877268344
                ],
                [
                    2.147066731369519,
                    13.470363306751322
                ],
                [
                    2.1472290475442484,
                    13.47042430988488
                ],
                [
                    2.1474870789348346,
                    13.470197710610174
                ],
                [
                    2.147584381751268,
                    13.469584953156996
                ],
                [
                    2.147597451391019,
                    13.469568848433932
                ],
                [
                    2.1475839727000645,
                    13.469123318343728
                ],
                [
                    2.1476191085233984,
                    13.46899638931188
                ],
                [
                    2.1476366224402015,
                    13.468959489530354
                ],
                [
                    2.147650417720226,
                    13.468959005623793
                ],
                [
                    2.1478517510231043,
                    13.469010097623611
                ],
                [
                    2.147902213573043,
                    13.469008918642446
                ],
                [
                    2.1480630442065993,
                    13.46873142243431
                ],
                [
                    2.148067414159967,
                    13.468672551317121
                ],
                [
                    2.1480544589224952,
                    13.46865635835804
                ],
                [
                    2.148049958398733,
                    13.468531924576036
                ],
                [
                    2.148037000136997,
                    13.46851658526112
                ],
                [
                    2.1479672371000396,
                    13.467936679759141
                ],
                [
                    2.1481025644187657,
                    13.467656392872408
                ],
                [
                    2.148036251966953,
                    13.467497675819764
                ],
                [
                    2.1480981489690127,
                    13.467366723528674
                ],
                [
                    2.148097211305618,
                    13.46733601418641
                ],
                [
                    2.148040882087882,
                    13.467255415221263
                ],
                [
                    2.1480891920159015,
                    13.46724670401536
                ],
                [
                    2.1480708548650025,
                    13.467097388481058
                ],
                [
                    2.1481193299941133,
                    13.467037118420324
                ],
                [
                    2.148145930957317,
                    13.466931871335541
                ],
                [
                    2.1481484807824036,
                    13.466788662264165
                ],
                [
                    2.148109785032563,
                    13.466727028334676
                ],
                [
                    2.1481281397933176,
                    13.46669468223455
                ],
                [
                    2.1481283029807132,
                    13.46664855873232
                ],
                [
                    2.1480894314264987,
                    13.466607096881578
                ],
                [
                    2.1480808259593958,
                    13.466574320867174
                ],
                [
                    2.148115062471809,
                    13.466392936440325
                ],
                [
                    2.1480583023003597,
                    13.466343937841211
                ],
                [
                    2.148010355979933,
                    13.46634000888851
                ],
                [
                    2.147971438093239,
                    13.466292527907507
                ],
                [
                    2.14785312649139,
                    13.466270293612052
                ],
                [
                    2.147758091900328,
                    13.466204570003185
                ],
                [
                    2.1478261962549294,
                    13.466152931253406
                ],
                [
                    2.1478276828520344,
                    13.466126702048651
                ],
                [
                    2.14767613428292,
                    13.466020431933734
                ],
                [
                    2.1472565373819847,
                    13.465814704112859
                ],
                [
                    2.147018787521545,
                    13.465678570962243
                ],
                [
                    2.146966193739855,
                    13.465635821922971
                ],
                [
                    2.1469512698598443,
                    13.465570897253217
                ],
                [
                    2.1467535048374846,
                    13.46539007251868
                ],
                [
                    2.146642986507992,
                    13.46540574457422
                ],
                [
                    2.1465834292031016,
                    13.4653888770119
                ],
                [
                    2.146549097064721,
                    13.4653478472971
                ],
                [
                    2.1464998865738436,
                    13.46533763721238
                ],
                [
                    2.146494187859037,
                    13.465289808015076
                ],
                [
                    2.146406108646711,
                    13.46522010170819
                ],
                [
                    2.1463067917198337,
                    13.465176037657448
                ],
                [
                    2.146263205339922,
                    13.465203706227612
                ],
                [
                    2.146225490998364,
                    13.46525740621223
                ],
                [
                    2.1461744334662174,
                    13.46522844414229
                ],
                [
                    2.146171814627908,
                    13.465203928297178
                ],
                [
                    2.1461175095760177,
                    13.465172097756437
                ],
                [
                    2.1460932023415427,
                    13.46512698811415
                ],
                [
                    2.1460524528391844,
                    13.465107958300626
                ],
                [
                    2.146041155034378,
                    13.465076228276143
                ],
                [
                    2.1459903475508733,
                    13.465043631913728
                ],
                [
                    2.1460351315599024,
                    13.464929776957279
                ],
                [
                    2.146104375576656,
                    13.464874468603329
                ],
                [
                    2.1460693024618203,
                    13.464556387615485
                ],
                [
                    2.1460827391648705,
                    13.464532385307317
                ],
                [
                    2.1460658412195723,
                    13.464470321314108
                ],
                [
                    2.145711264893156,
                    13.464417585976882
                ],
                [
                    2.1455500240497964,
                    13.464528809504678
                ],
                [
                    2.145491352899035,
                    13.464502563468162
                ],
                [
                    2.145430831755797,
                    13.464514939782319
                ],
                [
                    2.1453963187985954,
                    13.464470704635309
                ],
                [
                    2.145340161626327,
                    13.464434558094585
                ],
                [
                    2.1451647768854483,
                    13.46443432057247
                ],
                [
                    2.1450686335265594,
                    13.46439192994235
                ],
                [
                    2.1450188217878763,
                    13.464323995881832
                ],
                [
                    2.1449440546571643,
                    13.464324572993867
                ],
                [
                    2.1449120438652622,
                    13.464366396576972
                ],
                [
                    2.1448165291815338,
                    13.464307207734329
                ],
                [
                    2.1447379635012553,
                    13.464214338827615
                ],
                [
                    2.144739121060556,
                    13.464147834022109
                ],
                [
                    2.144724690275124,
                    13.464128796094442
                ],
                [
                    2.144624496924601,
                    13.464102405894682
                ],
                [
                    2.1445462437889304,
                    13.464119159034343
                ],
                [
                    2.1445250799818627,
                    13.46402740702884
                ],
                [
                    2.1443134236964045,
                    13.463957930865993
                ],
                [
                    2.1440588378841476,
                    13.463940168883477
                ],
                [
                    2.1438705285776187,
                    13.46375385750984
                ],
                [
                    2.143832171826952,
                    13.46375410627416
                ],
                [
                    2.1436912721291854,
                    13.463846802966161
                ],
                [
                    2.1436431477609146,
                    13.463812951391821
                ],
                [
                    2.1436170101641805,
                    13.463820992282344
                ],
                [
                    2.1436021330294386,
                    13.463796907628208
                ],
                [
                    2.143547545089141,
                    13.463771626863874
                ],
                [
                    2.143502936963388,
                    13.463781771292211
                ],
                [
                    2.143475857157762,
                    13.46374460538285
                ],
                [
                    2.143553390595192,
                    13.463620828428855
                ],
                [
                    2.143546461842466,
                    13.46359331718223
                ],
                [
                    2.143353757690689,
                    13.463650777276852
                ],
                [
                    2.1432288098189503,
                    13.463422915074666
                ],
                [
                    2.143058180857388,
                    13.463399516079459
                ],
                [
                    2.1430493496799303,
                    13.463386750188373
                ],
                [
                    2.1430309681792945,
                    13.463408510714784
                ],
                [
                    2.1430151064585936,
                    13.463378114225621
                ],
                [
                    2.1429978013197117,
                    13.463382029965468
                ],
                [
                    2.1429961531992516,
                    13.463408397431175
                ],
                [
                    2.142985455113825,
                    13.463372755951937
                ],
                [
                    2.142962506357656,
                    13.463378459941437
                ],
                [
                    2.1429475317659414,
                    13.463327015990762
                ],
                [
                    2.1429099787357315,
                    13.463310090781013
                ],
                [
                    2.1428998547640834,
                    13.463271478437543
                ],
                [
                    2.142857968733455,
                    13.463241759603957
                ],
                [
                    2.1428242051551103,
                    13.463184827828616
                ],
                [
                    2.1424483532057996,
                    13.463241960194644
                ],
                [
                    2.142130538915834,
                    13.463268566259801
                ],
                [
                    2.1421255860812485,
                    13.463337921741457
                ],
                [
                    2.142195118997444,
                    13.463622474575292
                ],
                [
                    2.141596223576107,
                    13.463825295414388
                ]
            ]
        ],
        "type": "Polygon"
    },
    "bbox": [
        2.1370853248373334,
        13.463184088597586,
        2.1481491809684594,
        13.477750894925727
    ],
    "links": [
        {
            "rel": "collection",
            "href": "../collection.json",
            "type": "application/json"
        },
        {
            "rel": "root",
            "href": "../../catalog.json",
            "type": "application/json"
        },
        {
            "rel": "parent",
            "href": "../collection.json",
            "type": "application/json"
        }
    ],
    "assets": {
        "labels": {
            "href": "https://drivendata-competition-building-segmentation.s3-us-west-1.amazonaws.com/train_tier_2/nia/982a1f-labels/982a1f.geojson",
            "type": "application/geo+json"
        },
        "image": {
            "href": "https://drivendata-competition-building-segmentation.s3-us-west-1.amazonaws.com/train_tier_2/nia/982a1f/982a1f.tif",
            "type": "image/tiff; application=geotiff; profile=cloud-optimized"
        }
    },
    "stac_extensions": [
        "label"
    ]
}